exinc
