Metadata-Version: 1.1
Name: cp-expand-includes
Version: 0.2.3
Summary: Expand includes for competitive programming
Home-page: UNKNOWN
Author: Roberto Sales
Author-email: UNKNOWN
License: MIT
Platform: UNKNOWN
Classifier: Programming Language :: Python
Classifier: Programming Language :: Python :: 2.7
